scattnlay_dp.cpython-311-darwin.so
scattnlay/__init__.py
scattnlay/main.py
python_scattnlay-2.4.dist-info/COPYING
python_scattnlay-2.4.dist-info/LICENSE
python_scattnlay-2.4.dist-info/METADATA
python_scattnlay-2.4.dist-info/WHEEL
python_scattnlay-2.4.dist-info/top_level.txt
python_scattnlay-2.4.dist-info/RECORD
