Metadata-Version: 2.1
Name: python-scattnlay
Version: 2.4
Summary: Calculation of the scattering of EM radiation by a multilayered sphere
Home-page: https://github.com/ovidiopr/scattnlay
Download-URL: https://github.com/ovidiopr/scattnlay/archive/v2.4.0.tar.gz
Author: Ovidio Peña Rodríguez
Author-email: Ovidio Peña <ovidio@bytesfall.com>, Konstantin Ladutenko <k.ladutenko@metalab.ifmo.ru>
Maintainer: Ovidio Peña Rodríguez
Maintainer-email: Ovidio Peña <ovidio@bytesfall.com>
License: GNU GENERAL PUBLIC LICENSE
Keywords: Light scattering
Platform: any
Classifier: Development Status :: 5 - Production/Stable
Classifier: Programming Language :: C++
Classifier: Programming Language :: Python
Requires-Python: >=3.8
License-File: LICENSE
License-File: COPYING
